<?xml version='1.0' encoding='utf-8'?>
<!DOCTYPE rules SYSTEM "https://resources.jetbrains.com/writerside/1.0/redirection-rules.dtd">
<rules>
    <rule id="1e77e8d0">
        <accepts>docker-techs.html</accepts>
        <accepts>qodana-docker-techs.html</accepts>
    </rule>
    <rule id="23895494">
        <accepts>docker-readme.html</accepts>
        <accepts>qodana-docker-readme.html</accepts>
    </rule>
    <rule id="4d0d5387">
        <accepts>teamcity-plugin.html</accepts>
    </rule>
</rules>
